[
  {
    "id": "CTwN0Qa2Xg47Z3mDdpJF",
    "job": "گەشەپێدەر/بەڕیوبەر",
    "facebook": "https://www.facebook.com/share/Z7C8FxBQPTTe3ZuV/?mibextid=qi2Omg",
    "name": "Shadman Othman",
    "snapchat": "",
    "twitter": "",
    "instagram": "https://www.instagram.com/shadman_osman1?igsh=MWF0N3QwcWcwZ2dpdw==",
    "description": "خوێندکاری کۆلێژی پزیشکی ڤێتیرنەری زانکۆی سلێمانی",
    "photo": "https://firebasestorage.googleapis.com/v0/b/vet-dict-93f36.appspot.com/o/staff_photos%2FShadman%20Othman.jpg?alt=media&token=a57b0167-37b1-498f-a293-fcfc4ef54b2f",
    "_exportedAt": "2025-06-06T19:36:51.162Z"
  },
  {
    "id": "Inxtev2evBQy4L4YfBvb",
    "name": "‌Harun Mubarak",
    "job": "بەڕیوبەر",
    "description": "خوێندکاری کۆلێژی پزیشکی ڤێتیرنەری زانکۆی سلێمانی",
    "facebook": "https://www.facebook.com/share/bxRPJG1fSeBoDisN/?mibextid=qi2Omg",
    "photo": "https://firebasestorage.googleapis.com/v0/b/vet-dict-93f36.appspot.com/o/staff_photos%2FHarun.jpg?alt=media&token=3616bc1f-18a9-4577-a71c-ba44027b5240",
    "snapchat": "",
    "twitter": "",
    "instagram": "https://www.instagram.com/harun_mubark?igsh=MWt0NmYyZjB1c2E5bA==",
    "_exportedAt": "2025-06-06T19:36:51.162Z"
  }
]